mqtt_logger/__init__.py
mqtt_logger/database.py
mqtt_logger/logger.py
mqtt_logger-0.3.6.dist-info/LICENSE
mqtt_logger-0.3.6.dist-info/METADATA
mqtt_logger-0.3.6.dist-info/WHEEL
mqtt_logger-0.3.6.dist-info/RECORD
