Metadata-Version: 2.1
Name: mqtt_logger
Version: 0.3.6
Summary: Python based MQTT to SQLite3 logger
Home-page: https://github.com/Blake-Haydon/mqtt-logger
License: MIT
Keywords: MQTT,SQLite3
Author: Blake Haydon
Author-email: blake.a.haydon@gmail.com
Requires-Python: >=3.7,<4.0
Classifier: License :: OSI Approved :: MIT License
Classifier: Programming Language :: Python :: 3
Classifier: Programming Language :: Python :: 3.7
Classifier: Programming Language :: Python :: 3.8
Classifier: Programming Language :: Python :: 3.9
Classifier: Programming Language :: Python :: 3.10
Classifier: Programming Language :: Python :: 3.11
Classifier: Programming Language :: Python :: 3.12
Requires-Dist: paho-mqtt (>=1.6.1,<2.0.0)
Requires-Dist: rich (>=12.0.0,<13.0.0)
